[
  {
    "@context": "https://schema.org",
    "@type": "Claim",
    "@id": "https://anchorfact.org/fact/fact-health-001",
    "text": "Yoga is an ancient physical, mental, and spiritual practice originating in India (5000+ years). Modern yoga in the West focuses on: asanas (postures), pranayama (breathing), meditation. Styles: Hatha (gentle, foundational), Vinyasa (flow, breath-linked movement), Ashtanga (vigorous, set sequence), Iyengar (alignment-focused), Yin (long-held passive",
    "anchorfact:confidence": "medium",
    "anchorfact:sourceRef": null,
    "anchorfact:sourceExcerpt": null,
    "anchorfact:verificationMethod": null,
    "citation": {
      "@type": "CreativeWork",
      "sameAs": "https://www.harpercollins.com/products/light-on-yoga-bks-iyengar?variant=32117613527074"
    }
  },
  {
    "@context": "https://schema.org",
    "@type": "Claim",
    "@id": "https://anchorfact.org/fact/fact-health-002",
    "text": "Key poses: Downward Dog, Warrior I/II/III, Child's Pose, Tree Pose, Cobra.",
    "anchorfact:confidence": "medium",
    "anchorfact:sourceRef": null,
    "anchorfact:sourceExcerpt": null,
    "anchorfact:verificationMethod": null,
    "citation": {
      "@type": "CreativeWork",
      "sameAs": "https://www.harpercollins.com/products/light-on-yoga-bks-iyengar?variant=32117613527074"
    }
  },
  {
    "@context": "https://schema.org",
    "@type": "Claim",
    "@id": "https://anchorfact.org/fact/fact-health-003",
    "text": "Sun Salutation (Surya Namaskar): sequence of 12 poses.",
    "anchorfact:confidence": "medium",
    "anchorfact:sourceRef": null,
    "anchorfact:sourceExcerpt": null,
    "anchorfact:verificationMethod": null,
    "citation": {
      "@type": "CreativeWork",
      "sameAs": "https://www.harpercollins.com/products/light-on-yoga-bks-iyengar?variant=32117613527074"
    }
  }
]