[
  {
    "@context": "https://schema.org",
    "@type": "Claim",
    "@id": "https://anchorfact.org/fact/fact-computer-science-01",
    "text": "MongoDB is a document-oriented NoSQL database first released in 2009 by MongoDB Inc",
    "anchorfact:confidence": "medium",
    "anchorfact:sourceRef": null,
    "anchorfact:sourceExcerpt": null,
    "anchorfact:verificationMethod": null,
    "citation": {
      "@type": "CreativeWork",
      "sameAs": "https://www.mongodb.com/docs/"
    }
  },
  {
    "@context": "https://schema.org",
    "@type": "Claim",
    "@id": "https://anchorfact.org/fact/fact-computer-science-002",
    "text": "Instead of tables and rows, it stores data as JSON-like BSON documents in collections, with a flexible schema.",
    "anchorfact:confidence": "medium",
    "anchorfact:sourceRef": null,
    "anchorfact:sourceExcerpt": null,
    "anchorfact:verificationMethod": null,
    "citation": {
      "@type": "CreativeWork",
      "sameAs": "https://www.mongodb.com/docs/"
    }
  },
  {
    "@context": "https://schema.org",
    "@type": "Claim",
    "@id": "https://anchorfact.org/fact/fact-computer-science-003",
    "text": "As of May 2026, MongoDB has 28,333 GitHub stars and is one of the most popular NoSQL databases, used by companies including Uber, eBay, and Bosch.",
    "anchorfact:confidence": "medium",
    "anchorfact:sourceRef": null,
    "anchorfact:sourceExcerpt": null,
    "anchorfact:verificationMethod": null,
    "citation": {
      "@type": "CreativeWork",
      "sameAs": "https://github.com/mongodb/mongo"
    }
  }
]