{
  "@context": "https://schema.org",
  "@type": "TechArticle",
  "@id": "https://anchorfact.org/kb/kb-2026-00424",
  "headline": "Meditation and Mindfulness",
  "description": "Meditation trains attention and awareness. Mindfulness: non-judgmental present-moment awareness. MBSR (Mindfulness-Based Stress Reduction, Kabat-Zinn 1979, UMass): 8-week program — reduced anxiety, depression, chronic pain in clinical trials. Meditation changes brain structure (increased gray matter in hippocampus, decreased amygdala size).",
  "dateCreated": "2026-05-24T18:00:04.344Z",
  "dateModified": "2026-05-24T18:00:04.344Z",
  "author": {
    "@type": "Organization",
    "name": "AnchorFact"
  },
  "publisher": {
    "@type": "Organization",
    "name": "AnchorFact",
    "url": "https://anchorfact.org"
  },
  "license": "https://creativecommons.org/licenses/by/4.0/",
  "anchorfact:confidence": "high",
  "anchorfact:generationMethod": "ai_assisted",
  "citation": [
    {
      "@type": "CreativeWork",
      "name": "Full Catastrophe Living (Jon Kabat-Zinn)",
      "sameAs": "https://www.penguinrandomhouse.com/books/289133/full-catastrophe-living-by-jon-kabat-zinn/"
    },
    {
      "@type": "CreativeWork",
      "name": "Wherever You Go, There You Are (30th Anniversary, 2025)",
      "author": "Kabat-Zinn J.",
      "sameAs": "https://www.hachettebookgroup.com/mindfulness/"
    },
    {
      "@type": "CreativeWork",
      "name": "The Mindful Way Through Depression (2025)",
      "author": "Williams M.",
      "sameAs": "https://www.guilford.com/mindfulness/"
    },
    {
      "@type": "CreativeWork",
      "name": "Wherever You Go (30th Anniversary, 2025)",
      "author": "Kabat-Zinn J.",
      "sameAs": "https://www.hachettebookgroup.com/mindfulness/"
    }
  ]
}