[
  {
    "@context": "https://schema.org",
    "@type": "Claim",
    "@id": "https://anchorfact.org/fact/fact-arts-001",
    "text": "Renaissance art (14th-16th centuries, Italy) revolutionized Western art through: linear perspective (Brunelleschi, ~1415), anatomical accuracy, chiaroscuro (light/shadow), sfumato (smoky blending, da Vinci), and humanistic themes. Patronage shifted from church to wealthy merchants (Medici).",
    "anchorfact:confidence": "medium",
    "citation": {
      "@type": "CreativeWork",
      "sameAs": "https://www.phaidon.com/store/art/the-story-of-art-pocket-edition-9780714872216/"
    }
  },
  {
    "@context": "https://schema.org",
    "@type": "Claim",
    "@id": "https://anchorfact.org/fact/fact-arts-002",
    "text": "Key works: Botticelli's Birth of Venus (1485), da Vinci's Last Supper (1498) and Mona Lisa (1503-19), Michelangelo's David (1504) and Sistine Chapel ceiling (1508-12), Raphael's School of Athens (1511).",
    "anchorfact:confidence": "medium",
    "citation": {
      "@type": "CreativeWork",
      "sameAs": "https://www.phaidon.com/store/art/the-story-of-art-pocket-edition-9780714872216/"
    }
  },
  {
    "@context": "https://schema.org",
    "@type": "Claim",
    "@id": "https://anchorfact.org/fact/fact-arts-003",
    "text": "Northern Renaissance: Van Eyck (oil painting innovations), Dürer, Bruegel.",
    "anchorfact:confidence": "medium",
    "citation": {
      "@type": "CreativeWork",
      "sameAs": "https://www.phaidon.com/store/art/the-story-of-art-pocket-edition-9780714872216/"
    }
  }
]